py2Dmol/__init__.py
py2Dmol/grid.py
py2Dmol/viewer.py
py2Dmol/resources/__init__.py
py2Dmol/resources/viewer-mol.min.js
py2Dmol/resources/viewer-pae.min.js
py2Dmol/resources/viewer-scatter.min.js
py2Dmol/resources/viewer.html
py2dmol-1.6.3.dist-info/licenses/LICENSE
py2dmol-1.6.3.dist-info/METADATA
py2dmol-1.6.3.dist-info/WHEEL
py2dmol-1.6.3.dist-info/top_level.txt
py2dmol-1.6.3.dist-info/RECORD
