Metadata-Version: 2.4
Name: py2Dmol
Version: 1.6.3
Summary: A Python library for visualizing protein structures in 2D.
Home-page: https://github.com/sokrypton/py2Dmol
Author: sokrypton
Author-email: so3@mit.edu
License: BEER-WARE
Classifier: Programming Language :: Python :: 3
Classifier: Operating System :: OS Independent
Requires-Python: >=3.6
License-File: LICENSE
Requires-Dist: numpy
Requires-Dist: ipython
Requires-Dist: gemmi
Dynamic: author
Dynamic: author-email
Dynamic: classifier
Dynamic: description
Dynamic: description-content-type
Dynamic: home-page
Dynamic: license
Dynamic: license-file
Dynamic: requires-dist
Dynamic: requires-python
Dynamic: summary
